locust/__init__.py
locust/clients.py
locust/core.py
locust/events.py
locust/exception.py
locust/inspectlocust.py
locust/log.py
locust/main.py
locust/runners.py
locust/stats.py
locust/web.py
locust/rpc/__init__.py
locust/rpc/protocol.py
locust/rpc/zmqrpc.py
locust/static/chart.js
locust/static/echarts.common.min.js
locust/static/jquery-1.11.3.min.js
locust/static/jquery.jqote2.min.js
locust/static/jquery.tools.min.js
locust/static/locust.js
locust/static/style.css
locust/static/vintage.js
locust/static/img/favicon.ico
locust/static/img/logo.png
locust/static/img/top_bg.png
locust/templates/index.html
locust/test/__init__.py
locust/test/test_client.py
locust/test/test_locust_class.py
locust/test/test_main.py
locust/test/test_parser.py
locust/test/test_runners.py
locust/test/test_stats.py
locust/test/test_task_sequence_class.py
locust/test/test_taskratio.py
locust/test/test_util.py
locust/test/test_web.py
locust/test/test_zmqrpc.py
locust/test/testcases.py
locust/util/__init__.py
locust/util/cache.py
locust/util/exception_handler.py
locust/util/rounding.py
locust/util/time.py
ddsl_locustio-0.11.4.dist-info/LICENSE
ddsl_locustio-0.11.4.dist-info/METADATA
ddsl_locustio-0.11.4.dist-info/WHEEL
ddsl_locustio-0.11.4.dist-info/entry_points.txt
ddsl_locustio-0.11.4.dist-info/top_level.txt
ddsl_locustio-0.11.4.dist-info/RECORD
